{
    "Insert General BlockTemplates": {
    "scope": "javascript,typescript,st",
    "prefix": ["fc, 1_simple"],
    "body": [

        "FUNCTION ${1:YourFcGeneralSimple1}",
        "\t// TODO please personalize block(name)",

        "\t",
        "\tVAR_INPUT",
        "\t\tmyInputVariable : INT;   //  add a constant to the given actual value",
        "\tEND_VAR",

        "\t",
        "\tVAR_OUTPUT",
        "\t\tmyOutputVariable : INT;   //  input value + constant",
        "\tEND_VAR",

        "\t",
        "\tVAR_TEMP",
        "\t\ttempVariable : INT;   //  temp value for anything",   
        "\tEND_VAR",

        "\t",
        "\tVAR CONSTANT",
        "\t\tTEMPORARY_INIT_VALUE : INT := 10;   //  value for the initialisation of the temporary tag",
        "\tEND_VAR",

        "${C:",
	    "\t//===============================================================================",
	    "\t// (company) / (c)Copyright (year)",
	    "\t//-------------------------------------------------------------------------------",
	    "\t// Title:            (Title of this Block)",
	    "\t// Comment/Function: (that is implemented in the block)",
	    "\t// Library/Family:   (that the source is dedicated to)",
	    "\t// Author:           (department / person in charge / contact)",
	    "\t// Tested with:      (test system with version)",
	    "\t// Engineering:      SIMATIC AX (SDK version)",
	    "\t// Restrictions:     (OB types, etc.)",
	    "\t// Requirements:     (hardware, technological package, memory needed, etc.)",
	    "\t//-------------------------------------------------------------------------------",
	    "\t// Change log table:",
	    "\t// Version  | Date       | Expert in charge       | Changes applied",
	    "\t//----------|------------|------------------------|------------------------------",
	    "\t// 01.00.00 | yyyy-mm-dd | (name of expert)       | First released version",
	    "\t//===============================================================================","}",

        "${C:",
        "    // TODO: Initialize functionality: reset of variables, diagnostics, etc.",
        "    //",       
        "    tempVariable := TEMPORARY_INIT_VALUE;",
        "    ",
        "    // TODO: Use this region for application specific code",
        "    //",
        "    // just an example code fragment",
        "    tempVariable := tempVariable + myInputVariable;",
        "    ",
        "    // TODO: Write application specific temp values to outputs",
        "    myOutputVariable := tempVariable;",
        "}",

        "END_FUNCTION"         
    ],
    "description": "[PLCOPEN-SNIPPETS] FC general (Simple V1)"
    }
}